bloxy/__init__.py
bloxy-0.0.0.dist-info/METADATA
bloxy-0.0.0.dist-info/WHEEL
bloxy-0.0.0.dist-info/top_level.txt
bloxy-0.0.0.dist-info/RECORD
