Metadata-Version: 2.1
Name: bloxy
Version: 0.0.0
Summary: lib
Home-page: https://github.com/user/project
Author: bloxy
Author-email: example@example.example
License: MIT
Classifier: License :: OSI Approved :: MIT License
